blessed/__init__.py
blessed/_capabilities.py
blessed/_capabilities.pyi
blessed/color.py
blessed/color.pyi
blessed/colorspace.py
blessed/colorspace.pyi
blessed/formatters.py
blessed/formatters.pyi
blessed/keyboard.py
blessed/keyboard.pyi
blessed/py.typed
blessed/sequences.py
blessed/sequences.pyi
blessed/terminal.py
blessed/terminal.pyi
blessed/win_terminal.py
blessed/win_terminal.pyi
blessed-1.20.0.dist-info/LICENSE
blessed-1.20.0.dist-info/METADATA
blessed-1.20.0.dist-info/WHEEL
blessed-1.20.0.dist-info/top_level.txt
blessed-1.20.0.dist-info/RECORD
