Metadata-Version: 2.1
Name: blessed
Version: 1.20.0
Summary: Easy, practical library for making terminal apps, by providing an elegant, well-documented interface to Colors, Keyboard input, and screen Positioning capabilities.
Home-page: https://github.com/jquast/blessed
Author: Jeff Quast, Erik Rose, Avram Lubkin
Author-email: contact@jeffquast.com
License: MIT
Project-URL: Documentation, https://blessed.readthedocs.io
Keywords: terminal,sequences,tty,curses,ncurses,formatting,style,color,console,keyboard,ansi,xterm
Classifier: Intended Audience :: Developers
Classifier: Natural Language :: English
Classifier: Development Status :: 5 - Production/Stable
Classifier: Environment :: Console
Classifier: Environment :: Console :: Curses
Classifier: License :: OSI Approved :: MIT License
Classifier: Operating System :: POSIX
Classifier: Operating System :: Microsoft :: Windows
Classifier: Programming Language :: Python :: 2
Classifier: Programming Language :: Python :: 2.7
Classifier: Programming Language :: Python :: 3
Classifier: Programming Language :: Python :: 3.4
Classifier: Programming Language :: Python :: 3.5
Classifier: Programming Language :: Python :: 3.6
Classifier: Programming Language :: Python :: 3.7
Classifier: Programming Language :: Python :: 3.8
Classifier: Programming Language :: Python :: 3.9
Classifier: Programming Language :: Python :: 3.10
Classifier: Programming Language :: Python :: 3.11
Classifier: Topic :: Software Development :: Libraries
Classifier: Topic :: Software Development :: User Interfaces
Classifier: Topic :: Terminals
Classifier: Typing :: Typed
Requires-Python: >=2.7
License-File: LICENSE
